[
  {"id":1,"arabic":"الرحمن","transliteration":"Ar-Rahman","meaning":"El Compasivo"},
  {"id":2,"arabic":"الرحيم","transliteration":"Ar-Rahim","meaning":"El Misericordioso"},
  {"id":3,"arabic":"الملك","transliteration":"Al-Malik","meaning":"El Rey"},
  {"id":4,"arabic":"القدوس","transliteration":"Al-Quddus","meaning":"El Santisimo"},
  {"id":5,"arabic":"السلام","transliteration":"As-Salam","meaning":"La Paz"},
  {"id":6,"arabic":"المؤمن","transliteration":"Al-Mu'min","meaning":"El que da seguridad"},
  {"id":7,"arabic":"المهيمن","transliteration":"Al-Muhaymin","meaning":"El Protector"},
  {"id":8,"arabic":"العزيز","transliteration":"Al-Aziz","meaning":"El Poderoso"},
  {"id":9,"arabic":"الجبار","transliteration":"Al-Jabbar","meaning":"El Irresistible"},
  {"id":10,"arabic":"المتكبر","transliteration":"Al-Mutakabbir","meaning":"El Sublime"},
  {"id":11,"arabic":"الخالق","transliteration":"Al-Khaliq","meaning":"El Creador"},
  {"id":12,"arabic":"البارئ","transliteration":"Al-Bari","meaning":"El Originador"},
  {"id":13,"arabic":"المصور","transliteration":"Al-Musawwir","meaning":"El Formador"},
  {"id":14,"arabic":"الغفار","transliteration":"Al-Ghaffar","meaning":"El Gran Perdonador"},
  {"id":15,"arabic":"القهار","transliteration":"Al-Qahhar","meaning":"El Dominador Supremo"},
  {"id":16,"arabic":"الوهاب","transliteration":"Al-Wahhab","meaning":"El Dador Generoso"},
  {"id":17,"arabic":"الرزاق","transliteration":"Ar-Razzaq","meaning":"El Sustentador"},
  {"id":18,"arabic":"الفتاح","transliteration":"Al-Fattah","meaning":"El que abre"},
  {"id":19,"arabic":"العليم","transliteration":"Al-Alim","meaning":"El Omnisciente"},
  {"id":20,"arabic":"القابض","transliteration":"Al-Qabid","meaning":"El que restringe"},
  {"id":21,"arabic":"الباسط","transliteration":"Al-Basit","meaning":"El que expande"},
  {"id":22,"arabic":"الخافض","transliteration":"Al-Khafid","meaning":"El que humilla"},
  {"id":23,"arabic":"الرافع","transliteration":"Ar-Rafi","meaning":"El que eleva"},
  {"id":24,"arabic":"المعز","transliteration":"Al-Muizz","meaning":"El que honra"},
  {"id":25,"arabic":"المذل","transliteration":"Al-Mudhill","meaning":"El que humilla a quien quiere"},
  {"id":26,"arabic":"السميع","transliteration":"As-Sami","meaning":"El que todo lo oye"},
  {"id":27,"arabic":"البصير","transliteration":"Al-Basir","meaning":"El que todo lo ve"},
  {"id":28,"arabic":"الحكم","transliteration":"Al-Hakam","meaning":"El Juez"},
  {"id":29,"arabic":"العدل","transliteration":"Al-Adl","meaning":"El Justo"},
  {"id":30,"arabic":"اللطيف","transliteration":"Al-Latif","meaning":"El Sutil y Bondadoso"},
  {"id":31,"arabic":"الخبير","transliteration":"Al-Khabir","meaning":"El Bien Informado"},
  {"id":32,"arabic":"الحليم","transliteration":"Al-Halim","meaning":"El Clemente"},
  {"id":33,"arabic":"العظيم","transliteration":"Al-Azim","meaning":"El Grandioso"},
  {"id":34,"arabic":"الغفور","transliteration":"Al-Ghafur","meaning":"El Perdonador"},
  {"id":35,"arabic":"الشكور","transliteration":"Ash-Shakur","meaning":"El Agradecido"},
  {"id":36,"arabic":"العلي","transliteration":"Al-Ali","meaning":"El Altisimo"},
  {"id":37,"arabic":"الكبير","transliteration":"Al-Kabir","meaning":"El Más Grande"},
  {"id":38,"arabic":"الحفيظ","transliteration":"Al-Hafiz","meaning":"El Preservador"},
  {"id":39,"arabic":"المقيت","transliteration":"Al-Muqit","meaning":"El Sustentador de todo"},
  {"id":40,"arabic":"الحسيب","transliteration":"Al-Hasib","meaning":"El que toma cuenta"},
  {"id":41,"arabic":"الجليل","transliteration":"Al-Jalil","meaning":"El Majestuoso"},
  {"id":42,"arabic":"الكريم","transliteration":"Al-Karim","meaning":"El Generosisimo"},
  {"id":43,"arabic":"الرقيب","transliteration":"Ar-Raqib","meaning":"El Vigilante"},
  {"id":44,"arabic":"المجيب","transliteration":"Al-Mujib","meaning":"El que responde"},
  {"id":45,"arabic":"الواسع","transliteration":"Al-Wasi","meaning":"El Amplio"},
  {"id":46,"arabic":"الحكيم","transliteration":"Al-Hakim","meaning":"El Sabio"},
  {"id":47,"arabic":"الودود","transliteration":"Al-Wadud","meaning":"El Amoroso"},
  {"id":48,"arabic":"المجيد","transliteration":"Al-Majid","meaning":"El Glorioso"},
  {"id":49,"arabic":"الباعث","transliteration":"Al-Baith","meaning":"El que resucita"},
  {"id":50,"arabic":"الشهيد","transliteration":"Ash-Shahid","meaning":"El Testigo"},
  {"id":51,"arabic":"الحق","transliteration":"Al-Haqq","meaning":"La Verdad"},
  {"id":52,"arabic":"الوكيل","transliteration":"Al-Wakil","meaning":"El Dispone de los asuntos"},
  {"id":53,"arabic":"القوي","transliteration":"Al-Qawiyy","meaning":"El Fuerte"},
  {"id":54,"arabic":"المتين","transliteration":"Al-Matin","meaning":"El Firme"},
  {"id":55,"arabic":"الولي","transliteration":"Al-Wali","meaning":"El Protector Cercano"},
  {"id":56,"arabic":"الحميد","transliteration":"Al-Hamid","meaning":"El Loable"},
  {"id":57,"arabic":"المحصي","transliteration":"Al-Muhsi","meaning":"El que todo lo enumera"},
  {"id":58,"arabic":"المبدئ","transliteration":"Al-Mubdi","meaning":"El Originador"},
  {"id":59,"arabic":"المعيد","transliteration":"Al-Muid","meaning":"El Restaurador"},
  {"id":60,"arabic":"المحيي","transliteration":"Al-Muhyi","meaning":"El Dador de vida"},
  {"id":61,"arabic":"المميت","transliteration":"Al-Mumit","meaning":"El que da la muerte"},
  {"id":62,"arabic":"الحي","transliteration":"Al-Hayy","meaning":"El Viviente"},
  {"id":63,"arabic":"القيوم","transliteration":"Al-Qayyum","meaning":"El Autosubsistente"},
  {"id":64,"arabic":"الواجد","transliteration":"Al-Wajid","meaning":"El que encuentra todo"},
  {"id":65,"arabic":"الماجد","transliteration":"Al-Majid","meaning":"El Noble y Glorioso"},
  {"id":66,"arabic":"الواحد","transliteration":"Al-Wahid","meaning":"El Unico"},
  {"id":67,"arabic":"الأحد","transliteration":"Al-Ahad","meaning":"El Uno"},
  {"id":68,"arabic":"الصمد","transliteration":"As-Samad","meaning":"El Absoluto"},
  {"id":69,"arabic":"القادر","transliteration":"Al-Qadir","meaning":"El Omnipotente"},
  {"id":70,"arabic":"المقتدر","transliteration":"Al-Muqtadir","meaning":"El Determinante"},
  {"id":71,"arabic":"المقدم","transliteration":"Al-Muqaddim","meaning":"El que adelanta"},
  {"id":72,"arabic":"المؤخر","transliteration":"Al-Muakhkhir","meaning":"El que retrasa"},
  {"id":73,"arabic":"الأول","transliteration":"Al-Awwal","meaning":"El Primero"},
  {"id":74,"arabic":"الآخر","transliteration":"Al-Akhir","meaning":"El Último"},
  {"id":75,"arabic":"الظاهر","transliteration":"Az-Zahir","meaning":"El Manifiesto"},
  {"id":76,"arabic":"الباطن","transliteration":"Al-Batin","meaning":"El Oculto"},
  {"id":77,"arabic":"الوالي","transliteration":"Al-Wali","meaning":"El Gobernante"},
  {"id":78,"arabic":"المتعالي","transliteration":"Al-Mutaali","meaning":"El Altisimo sobre todo"},
  {"id":79,"arabic":"البر","transliteration":"Al-Barr","meaning":"El Bueno"},
  {"id":80,"arabic":"التواب","transliteration":"At-Tawwab","meaning":"El que acepta el arrepentimiento"},
  {"id":81,"arabic":"المنتقم","transliteration":"Al-Muntaqim","meaning":"El Justiciero"},
  {"id":82,"arabic":"العفو","transliteration":"Al-Afuww","meaning":"El Indulgente"},
  {"id":83,"arabic":"الرؤوف","transliteration":"Ar-Ra'uf","meaning":"El Compasivo con ternura"},
  {"id":84,"arabic":"مالك الملك","transliteration":"Malik-ul-Mulk","meaning":"El Dueño del Reino"},
  {"id":85,"arabic":"ذو الجلال والإكرام","transliteration":"Dhul-Jalali wal-Ikram","meaning":"Señor de la Majestad y la Generosidad"},
  {"id":86,"arabic":"المقسط","transliteration":"Al-Muqsit","meaning":"El Equitativo"},
  {"id":87,"arabic":"الجامع","transliteration":"Al-Jami","meaning":"El Reunidor"},
  {"id":88,"arabic":"الغني","transliteration":"Al-Ghani","meaning":"El Rico, el Autosuficiente"},
  {"id":89,"arabic":"المغني","transliteration":"Al-Mughni","meaning":"El que enriquece"},
  {"id":90,"arabic":"المانع","transliteration":"Al-Mani","meaning":"El que impide"},
  {"id":91,"arabic":"الضار","transliteration":"Ad-Darr","meaning":"El que permite la adversidad"},
  {"id":92,"arabic":"النافع","transliteration":"An-Nafi","meaning":"El que otorga beneficio"},
  {"id":93,"arabic":"النور","transliteration":"An-Nur","meaning":"La Luz"},
  {"id":94,"arabic":"الهادي","transliteration":"Al-Hadi","meaning":"El Guia"},
  {"id":95,"arabic":"البديع","transliteration":"Al-Badi","meaning":"El Incomparable Originador"},
  {"id":96,"arabic":"الباقي","transliteration":"Al-Baqi","meaning":"El Eterno"},
  {"id":97,"arabic":"الوارث","transliteration":"Al-Warith","meaning":"El Heredero de todo"},
  {"id":98,"arabic":"الرشيد","transliteration":"Ar-Rashid","meaning":"El que guia con rectitud"},
  {"id":99,"arabic":"الصبور","transliteration":"As-Sabur","meaning":"El Paciente"}
]
