[{"n":"Albadéria","nn":"albaderia","lat":9.55,"lng":-10.1},{"n":"Arfa Moussaïa","nn":"arfa moussaia","lat":10.76667,"lng":-11.36667},{"n":"Banko","nn":"banko","lat":10.71667,"lng":-10.71667},{"n":"Beyla","nn":"beyla","lat":8.69011,"lng":-8.64869},{"n":"Bissikrima","nn":"bissikrima","lat":10.85,"lng":-10.93333},{"n":"Boffa","nn":"boffa","lat":10.16667,"lng":-14.03333},{"n":"Boké","nn":"boke","lat":10.93217,"lng":-14.29055},{"n":"Camayenne","nn":"camayenne","lat":9.535,"lng":-13.68778},{"n":"Conakry","nn":"conakry","lat":9.53795,"lng":-13.67729},{"n":"Coyah","nn":"coyah","lat":9.70643,"lng":-13.38465},{"n":"Dabola","nn":"dabola","lat":10.7433,"lng":-11.10778},{"n":"Dalaba","nn":"dalaba","lat":10.69249,"lng":-12.24967},{"n":"Dinguiraye","nn":"dinguiraye","lat":11.29062,"lng":-10.7121},{"n":"Dixinn","nn":"dixinn","lat":9.55111,"lng":-13.67306},{"n":"Dogomet","nn":"dogomet","lat":10.58906,"lng":-11.17752},{"n":"Donghol-Sigon","nn":"donghol-sigon","lat":11.8,"lng":-12.2167},{"n":"Douako","nn":"douako","lat":9.73333,"lng":-10.18333},{"n":"Dubréka","nn":"dubreka","lat":9.79111,"lng":-13.52333},{"n":"Faranah","nn":"faranah","lat":10.04036,"lng":-10.74343},{"n":"Forécariah","nn":"forecariah","lat":9.43056,"lng":-13.08806},{"n":"Fria","nn":"fria","lat":10.36676,"lng":-13.58253},{"n":"Gaoual","nn":"gaoual","lat":11.75,"lng":-13.2},{"n":"Gueckedou","nn":"gueckedou","lat":8.56744,"lng":-10.1336},{"n":"Kamabi","nn":"kamabi","lat":12.4,"lng":-13.41667},{"n":"Kamsar","nn":"kamsar","lat":10.65,"lng":-14.61667},{"n":"Kankan","nn":"kankan","lat":10.38542,"lng":-9.30568},{"n":"Kimbo","nn":"kimbo","lat":10.4,"lng":-13.55},{"n":"Kindia","nn":"kindia","lat":10.05692,"lng":-12.86576},{"n":"Kintinian","nn":"kintinian","lat":11.6,"lng":-9.38333},{"n":"Kissidougou","nn":"kissidougou","lat":9.1848,"lng":-10.09987},{"n":"Kolaboui","nn":"kolaboui","lat":10.79569,"lng":-14.39966},{"n":"Kolenté","nn":"kolente","lat":10.28578,"lng":-12.43699},{"n":"Koubia","nn":"koubia","lat":11.58632,"lng":-11.89485},{"n":"Koumbia","nn":"koumbia","lat":11.8,"lng":-13.5},{"n":"Koundara","nn":"koundara","lat":12.48333,"lng":-13.3},{"n":"Kouroussa","nn":"kouroussa","lat":10.65,"lng":-9.88333},{"n":"Kérouané","nn":"kerouane","lat":9.26667,"lng":-9.01667},{"n":"Labé","nn":"labe","lat":11.31823,"lng":-12.28332},{"n":"Lola","nn":"lola","lat":7.8,"lng":-8.53333},{"n":"Lélouma","nn":"lelouma","lat":11.42383,"lng":-12.68183},{"n":"Macenta","nn":"macenta","lat":8.54351,"lng":-9.47099},{"n":"Mali","nn":"mali","lat":12.079,"lng":-12.2982},{"n":"Mamou","nn":"mamou","lat":10.37546,"lng":-12.09148},{"n":"Mandiana","nn":"mandiana","lat":10.62577,"lng":-8.69413},{"n":"Manéah","nn":"maneah","lat":9.73333,"lng":-13.41667},{"n":"Moussadou","nn":"moussadou","lat":8.76667,"lng":-8.61667},{"n":"Nongoa","nn":"nongoa","lat":9.98333,"lng":-10.15},{"n":"Nzérékoré","nn":"nzerekore","lat":7.75624,"lng":-8.8179},{"n":"Pita","nn":"pita","lat":11.05915,"lng":-12.39498},{"n":"Sangarédi","nn":"sangaredi","lat":11.1,"lng":-13.76667},{"n":"Sanguéya","nn":"sangueya","lat":10.7,"lng":-14.36667},{"n":"Selouma","nn":"selouma","lat":11.11667,"lng":-10.98333},{"n":"Siguiri","nn":"siguiri","lat":11.42282,"lng":-9.16852},{"n":"Timbo","nn":"timbo","lat":10.63333,"lng":-11.83333},{"n":"Tokonou","nn":"tokonou","lat":9.65,"lng":-9.78333},{"n":"Tomba-kanssa","nn":"tomba-kanssa","lat":11.72321,"lng":-10.18899},{"n":"Tondon","nn":"tondon","lat":10.36667,"lng":-13.35},{"n":"Tougué","nn":"tougue","lat":11.44503,"lng":-11.66422},{"n":"Télimélé","nn":"telimele","lat":10.9,"lng":-13.03333},{"n":"Wendou Borou","nn":"wendou borou","lat":11.43333,"lng":-13.88333},{"n":"Yende Millimou","nn":"yende millimou","lat":8.88722,"lng":-10.17222},{"n":"Yomou","nn":"yomou","lat":7.56748,"lng":-9.26283},{"n":"Youkounkoun","nn":"youkounkoun","lat":12.5311,"lng":-13.1224}]