[{"n":"Castel","nn":"castel","lat":49.46757,"lng":-2.60015},{"n":"Forest Parish","nn":"forest parish","lat":49.42983,"lng":-2.60168},{"n":"Saint Andrew","nn":"saint andrew","lat":49.44389,"lng":-2.58018},{"n":"Saint Peter Port","nn":"saint peter port","lat":49.45981,"lng":-2.53527},{"n":"Saint Pierre du Bois Parish","nn":"saint pierre du bois parish","lat":49.45399,"lng":-2.63808},{"n":"Saint Sampson","nn":"saint sampson","lat":49.48389,"lng":-2.52333},{"n":"Saint Saviour","nn":"saint saviour","lat":49.45694,"lng":-2.63583},{"n":"St Anne","nn":"st anne","lat":49.71549,"lng":-2.20757},{"n":"St Martin","nn":"st martin","lat":49.43713,"lng":-2.55479},{"n":"Torteval","nn":"torteval","lat":49.43333,"lng":-2.65},{"n":"Vale Parish","nn":"vale parish","lat":49.4944,"lng":-2.5179}]